st_dialog_close_detector/__init__.py
st_dialog_close_detector/py.typed
st_dialog_close_detector/frontend/index.html
st_dialog_close_detector/frontend/main.js
st_dialog_close_detector/frontend/package.json
st_dialog_close_detector/frontend/vite.config.js
st_dialog_close_detector/frontend/dist/index.html
st_dialog_close_detector/frontend/dist/assets/index-TvAJ7Vpq.js
st_dialog_close_detector-0.1.2.dist-info/METADATA
st_dialog_close_detector-0.1.2.dist-info/WHEEL
st_dialog_close_detector-0.1.2.dist-info/RECORD
