Metadata-Version: 2.4
Name: st-dialog-close-detector
Version: 0.1.2
Summary: Automatically rerun Streamlit app when a dialog is closed
Project-URL: repository, https://github.com/hoishing/st-dialog-close-detector
Author-email: Kelvin Ng <hoishing@gmail.com>
Requires-Python: >=3.12
Requires-Dist: streamlit>=1.44.1
